quantum_parser/__init__.py
quantum_parser/c_fusion_linker/__init__.py
quantum_parser/c_fusion_linker/c_fusion_linker.py
quantum_parser/qasm2_parser/__init__.py
quantum_parser/qasm2_parser/qasm2_parser.py
quantum_parser/qcis_parser/__init__.py
quantum_parser/qcis_parser/qcis_parser.py
quantum_parser-1.1.1.dist-info/licenses/LICENSE
quantum_parser-1.1.1.dist-info/METADATA
quantum_parser-1.1.1.dist-info/WHEEL
quantum_parser-1.1.1.dist-info/top_level.txt
quantum_parser-1.1.1.dist-info/RECORD
