Metadata-Version: 2.4
Name: quantum_parser
Version: 1.1.1
Summary: A package parsing various quantum circuits.
Author-email: Yusheng Yang <yangys@arclightquantum.com>
License-File: LICENSE
Dynamic: license-file
